context_cleaner/__init__.py
context_cleaner/__main__.py
context_cleaner/analysis/__init__.py
context_cleaner/analysis/context_window_analyzer.py
context_cleaner/analysis/correlation_analyzer.py
context_cleaner/analysis/dashboard_integration.py
context_cleaner/analysis/discovery.py
context_cleaner/analysis/enhanced_context_analyzer.py
context_cleaner/analysis/enhanced_token_counter.py
context_cleaner/analysis/models.py
context_cleaner/analysis/project_summary_analytics.py
context_cleaner/analysis/session_parser.py
context_cleaner/analysis/summary_parser.py
context_cleaner/analysis/temporal_analyzer.py
context_cleaner/analysis/token_analyzer.py
context_cleaner/analysis/usage_analyzer.py
context_cleaner/analytics/__init__.py
context_cleaner/analytics/advanced_patterns.py
context_cleaner/analytics/anomaly_detector.py
context_cleaner/analytics/business_intelligence.py
context_cleaner/analytics/content_intelligence.py
context_cleaner/analytics/context_health_scorer.py
context_cleaner/analytics/correlation_analyzer.py
context_cleaner/analytics/effectiveness_tracker.py
context_cleaner/analytics/predictive_intelligence.py
context_cleaner/analytics/predictive_models.py
context_cleaner/analytics/productivity_analyzer.py
context_cleaner/analytics/recommendation_engine.py
context_cleaner/analytics/seasonal_patterns.py
context_cleaner/analytics/trend_analyzer.py
context_cleaner/api/__init__.py
context_cleaner/api/app.py
context_cleaner/api/cache.py
context_cleaner/api/cache_manager.py
context_cleaner/api/integration.py
context_cleaner/api/models.py
context_cleaner/api/repositories.py
context_cleaner/api/response_optimization.py
context_cleaner/api/services.py
context_cleaner/api/websocket.py
context_cleaner/bridges/__init__.py
context_cleaner/bridges/incremental_sync.py
context_cleaner/bridges/token_analysis_bridge.py
context_cleaner/cli/__init__.py
context_cleaner/cli/__main__.py
context_cleaner/cli/analytics_commands.py
context_cleaner/cli/main.py
context_cleaner-0.3.0.dist-info/METADATA
context_cleaner-0.3.0.dist-info/WHEEL
context_cleaner-0.3.0.dist-info/entry_points.txt
context_cleaner-0.3.0.dist-info/licenses/LICENSE
context_cleaner-0.3.0.dist-info/RECORD
