Metadata-Version: 2.4
Name: context-cleaner
Version: 0.3.0
Summary: Advanced productivity tracking and context optimization for AI-assisted development
Project-URL: Homepage, https://github.com/context-cleaner/context-cleaner
Project-URL: Documentation, https://context-cleaner.readthedocs.io
Project-URL: Repository, https://github.com/context-cleaner/context-cleaner
Project-URL: Issues, https://github.com/context-cleaner/context-cleaner/issues
Author-email: Context Cleaner Team <team@context-cleaner.dev>
License: MIT
License-File: LICENSE
Classifier: Development Status :: 5 - Production/Stable
Classifier: Intended Audience :: Developers
Classifier: License :: OSI Approved :: MIT License
Classifier: Programming Language :: Python :: 3
Classifier: Programming Language :: Python :: 3.9
Classifier: Programming Language :: Python :: 3.10
Classifier: Programming Language :: Python :: 3.11
Classifier: Programming Language :: Python :: 3.12
Classifier: Topic :: Software Development :: Libraries :: Python Modules
Requires-Python: >=3.9
Requires-Dist: aiofiles>=23.1.0
Requires-Dist: aiohttp>=3.9.0
Requires-Dist: apscheduler>=3.10.4
Requires-Dist: click>=8.1.0
Requires-Dist: croniter>=1.4.0
Requires-Dist: cryptography>=41.0.0
Requires-Dist: eventlet<0.40,>=0.33.0
Requires-Dist: fastapi>=0.110.0
Requires-Dist: flask-socketio>=5.3.0
Requires-Dist: flask>=2.3.0
Requires-Dist: gitpython>=3.1.40
Requires-Dist: gunicorn>=21.2.0
Requires-Dist: matplotlib>=3.8.0
Requires-Dist: nltk>=3.8.1
Requires-Dist: numpy>=1.24.0
Requires-Dist: orjson>=3.9.0
Requires-Dist: pandas>=2.0.0
Requires-Dist: plotly>=5.17.0
Requires-Dist: protobuf>=4.25.0
Requires-Dist: psutil>=5.9.0
Requires-Dist: pydantic>=2.5.0
Requires-Dist: python-dateutil>=2.8.2
Requires-Dist: pytz>=2023.3
Requires-Dist: pyyaml>=6.0
Requires-Dist: redis>=5.0.0
Requires-Dist: requests>=2.31.0
Requires-Dist: scikit-learn>=1.3.0
Requires-Dist: sqlalchemy>=2.0.0
Requires-Dist: textblob>=0.17.1
Requires-Dist: watchdog>=3.0.0
Requires-Dist: websockets>=10.0
Provides-Extra: dev
Requires-Dist: black>=23.9.0; extra == 'dev'
Requires-Dist: flake8>=6.1.0; extra == 'dev'
Requires-Dist: mypy>=1.6.0; extra == 'dev'
Requires-Dist: pytest-asyncio>=0.21.0; extra == 'dev'
Requires-Dist: pytest-cov>=4.1.0; extra == 'dev'
Requires-Dist: pytest>=7.4.0; extra == 'dev'
Provides-Extra: docs
Requires-Dist: mkdocs-material>=9.4.0; extra == 'docs'
Requires-Dist: mkdocs>=1.5.0; extra == 'docs'
